madx_ptc_utils/__init__.py
madx_ptc_utils/create_ptc_files.py
madx_ptc_utils/python_from_ptc.py
madx_ptc_utils/rm_keyword.py
madx_ptc_utils-0.1.4.dist-info/METADATA
madx_ptc_utils-0.1.4.dist-info/WHEEL
madx_ptc_utils-0.1.4.dist-info/entry_points.txt
madx_ptc_utils-0.1.4.dist-info/licenses/LICENSE
madx_ptc_utils-0.1.4.dist-info/RECORD
