Metadata-Version: 2.4
Name: madx-ptc-utils
Version: 0.1.4
Summary: Uses MAD-X PTC to convert a MAD-X lattice to a Python object
Project-URL: Homepage, https://github.com/anderske-msu/madx-ptc-utils
Project-URL: Bug Tracker, https://github.com/anderske-msu/madx-ptc-utils/issues
Author-email: Kelly Anderson <kjanderson24@proton.me>
License:                     GNU GENERAL PUBLIC LICENSE
License-File: LICENSE
Keywords: MAD-X,PTC,madx,particle tracking
Classifier: License :: OSI Approved :: GNU General Public License v3 (GPLv3)
Classifier: License :: OSI Approved :: GNU General Public License v3 or later (GPLv3+)
Classifier: Programming Language :: Python :: 3
Classifier: Programming Language :: Python :: 3.10
Classifier: Programming Language :: Python :: 3.11
Requires-Python: >=3.10
Requires-Dist: cpymad
Requires-Dist: numpy
